{
  "name": "${localWorkspaceFolderBasename}",
  "dockerComposeFile": "docker-compose.yml",
  "service": "dev",
  "workspaceFolder": "/workspaces/${localWorkspaceFolderBasename}",
  "customizations": {
    "vscode": {
      "extensions": [
        "usernamehw.errorlens",
        "streetsidesoftware.code-spell-checker",
        "redhat.vscode-yaml",
        "amazonwebservices.amazon-q-vscode",
        "GitHub.copilot-chat"
      ],
      "settings": {
        "terminal.integrated.defaultProfile.linux": "tmux",
        "editor.formatOnSave": true,
        "editor.formatOnType": false,
        "editor.formatOnPaste": true,
        "editor.formatOnSaveMode": "file",
        "files.autoSave": "onFocusChange"
      }
    }
  },
  "postCreateCommand": "/bin/sh /usr/src/post_create.sh",
  "remoteUser": "vscode"
}
